v_tag.py
v_tag-0.1.0.dist-info/LICENSE
v_tag-0.1.0.dist-info/METADATA
v_tag-0.1.0.dist-info/WHEEL
v_tag-0.1.0.dist-info/entry_points.txt
v_tag-0.1.0.dist-info/top_level.txt
v_tag-0.1.0.dist-info/RECORD
